data_market_index_fetcher/__init__.py
data_market_index_fetcher/indexes/__init__.py
data_market_index_fetcher/indexes/ibov/__init__.py
data_market_index_fetcher/indexes/ibov/ibov_metadata.json
data_market_index_fetcher/indexes/ibov/IbovWebScrapperB3.py
data_market_index_fetcher/indexes/ibov/README.md
data_market_index_fetcher/indexes/ibov/requirements.txt
data_market_index_fetcher/indexes/ibov/TestIbovWebScrapper.py
data_market_index_fetcher/indexes/ibov/utils/__init__.py
data_market_index_fetcher/indexes/ibov/utils/DateUtil.py
data_market_index_fetcher/indexes/ibov/utils/LoggerUtil.py
data_market_index_fetcher/indexes/ibov/utils/SeleniumUtil.py
data_market_index_fetcher/indexes/ibov/utils/WebDriverUtil.py
data_market_index_fetcher-1.1.2.dist-info/LICENSE
data_market_index_fetcher-1.1.2.dist-info/METADATA
data_market_index_fetcher-1.1.2.dist-info/WHEEL
data_market_index_fetcher-1.1.2.dist-info/RECORD
