Metadata-Version: 2.3
Name: data_market_index_fetcher
Version: 1.1.2
Summary: 
Author: Flavio Lopes
Author-email: fnldesign@hotmail.com
Requires-Python: >=3.10,<4.0
Classifier: Programming Language :: Python :: 3
Classifier: Programming Language :: Python :: 3.10
Classifier: Programming Language :: Python :: 3.11
Classifier: Programming Language :: Python :: 3.12
Classifier: Programming Language :: Python :: 3.13
Requires-Dist: attrs (==24.3.0)
Requires-Dist: certifi (==2024.12.14)
Requires-Dist: cffi (==1.17.1)
Requires-Dist: charset-normalizer (==3.4.1)
Requires-Dist: exceptiongroup (==1.2.2)
Requires-Dist: h11 (==0.14.0)
Requires-Dist: idna (==3.10)
Requires-Dist: numpy (==2.2.1)
Requires-Dist: outcome (==1.3.0.post0)
Requires-Dist: packaging (==24.2)
Requires-Dist: pandas (==2.2.3)
Requires-Dist: pycparser (==2.22)
Requires-Dist: pysocks (==1.7.1)
Requires-Dist: python-dateutil (==2.9.0.post0)
Requires-Dist: python-dotenv (==1.0.1)
Requires-Dist: pytz (==2024.2)
Requires-Dist: requests (==2.32.3)
Requires-Dist: selenium (==4.27.1)
Requires-Dist: six (==1.17.0)
Requires-Dist: sniffio (==1.3.1)
Requires-Dist: sortedcontainers (==2.4.0)
Requires-Dist: trio (==0.28.0)
Requires-Dist: trio-websocket (==0.11.1)
Requires-Dist: typing-extensions (==4.12.2)
Requires-Dist: tzdata (==2024.2)
Requires-Dist: urllib3 (==2.3.0)
Requires-Dist: webdriver-manager (==4.0.2)
Requires-Dist: websocket-client (==1.8.0)
Requires-Dist: wsproto (==1.2.0)
